mprov_esxiprovisioner/__init__.py
mprov_esxiprovisioner/admin.py
mprov_esxiprovisioner/apps.py
mprov_esxiprovisioner/middleware.py
mprov_esxiprovisioner/models.py
mprov_esxiprovisioner/serializers.py
mprov_esxiprovisioner/views.py
mprov_esxiprovisioner/templates/systems/ipxe
mprov_esxiprovisioner-0.0.3.dist-info/LICENSE
mprov_esxiprovisioner-0.0.3.dist-info/METADATA
mprov_esxiprovisioner-0.0.3.dist-info/WHEEL
mprov_esxiprovisioner-0.0.3.dist-info/top_level.txt
mprov_esxiprovisioner-0.0.3.dist-info/RECORD
