Metadata-Version: 2.1
Name: mprov-esxiprovisioner
Version: 0.0.3
Summary: An add-on to the mPCC to enable it to provision ESXi servers
Home-page: https://github.com/mprov-ng/mprov_esxiprovisioner
Author: Jason Williams
Author-email: jasonw@jhu.edu
Project-URL: Bug Tracker, https://github.com/mprov-ng/mprov_esxiprovisioner/issues
Classifier: Programming Language :: Python :: 3
Classifier: Operating System :: POSIX :: Linux
Classifier: License :: OSI Approved :: Apache Software License
Requires-Python: >=3.8
License-File: LICENSE
Requires-Dist: sh
